samaware/__init__.py
samaware/apps.py
samaware/forms.py
samaware/models.py
samaware/queries.py
samaware/signals.py
samaware/tables.py
samaware/urls.py
samaware/views.py
samaware/migrations/0001_initial.py
samaware/migrations/0002_techrider.py
samaware/migrations/0003_techrider_last_sync_techrider_sync_dirty_and_more.py
samaware/migrations/0004_remove_samawaresettings_event_and_more.py
samaware/migrations/__init__.py
samaware/static/samaware/samaware.css
samaware/static/samaware/samaware.js
samaware/static/samaware/samovar.svg
samaware/static/samaware/vendor/htmx.min.js
samaware/templates/samaware/care_message_edit.html
samaware/templates/samaware/care_message_list.html
samaware/templates/samaware/dashboard.html
samaware/templates/samaware/missing_speakers_list.html
samaware/templates/samaware/no_recording_list.html
samaware/templates/samaware/talk_overview.html
samaware/templates/samaware/tech_rider_edit.html
samaware/templates/samaware/tech_rider_list.html
samaware/templates/samaware/fragments/form_or_content.html
samaware/templates/samaware/fragments/search_result.html
samaware/templates/samaware/table_cols/speakers.html
samaware/templates/samaware/table_cols/track.html
samaware/templates/samaware/table_cols/truncate_text.html
samaware/templatetags/__init__.py
samaware/templatetags/samaware_extras.py
samaware-2.1.0.dist-info/licenses/LICENSE.txt
samaware-2.1.0.dist-info/METADATA
samaware-2.1.0.dist-info/WHEEL
samaware-2.1.0.dist-info/entry_points.txt
samaware-2.1.0.dist-info/top_level.txt
samaware-2.1.0.dist-info/RECORD
