Metadata-Version: 2.4
Name: samaware
Version: 2.1.0
Summary: pretalx plugin with enhanced features for speaker care during a conference
Author-email: Felix Dreissig <f30@f30.me>
License-Expression: ISC
Project-URL: homepage, https://github.com/f30/samaware
Project-URL: repository, https://github.com/f30/samaware.git
Project-URL: Issues, https://github.com/f30/samaware/issues
Keywords: pretalx,conference,event,plugin
Classifier: Development Status :: 5 - Production/Stable
Classifier: Environment :: Web Environment
Classifier: Environment :: Plugins
Classifier: Framework :: Django
Classifier: Topic :: Internet :: WWW/HTTP :: Dynamic Content
Requires-Python: >=3.10
License-File: LICENSE.txt
Requires-Dist: django-context-decorator
Requires-Dist: django-csp>=4.0
Requires-Dist: django-scopes
Requires-Dist: django-tables2
Provides-Extra: dev
Requires-Dist: build; extra == "dev"
Requires-Dist: setuptools; extra == "dev"
Requires-Dist: ruff; extra == "dev"
Requires-Dist: pylint; extra == "dev"
Requires-Dist: pytest; extra == "dev"
Requires-Dist: pytest-django; extra == "dev"
Dynamic: license-file
